ae_ffmpeg/__init__.py
ae_ffmpeg/py.typed
ae_ffmpeg-1.2.0.dist-info/LICENSE.txt
ae_ffmpeg-1.2.0.dist-info/METADATA
ae_ffmpeg-1.2.0.dist-info/WHEEL
ae_ffmpeg-1.2.0.dist-info/top_level.txt
ae_ffmpeg-1.2.0.dist-info/RECORD
