Metadata-Version: 2.1
Name: ae-ffmpeg
Version: 1.2.0
Summary: Static FFmpeg binaries for Auto-Editor
Home-page: https://auto-editor.com
Author: WyattBlue
Author-email: wyattblue@auto-editor.com
License: LGPLv3
Project-URL: Bug Tracker, https://github.com/WyattBlue/auto-editor/issues
Project-URL: Source Code, https://github.com/WyattBlue/auto-editor
Keywords: video audio media
Classifier: Topic :: Multimedia :: Sound/Audio
Classifier: Topic :: Multimedia :: Video
Classifier: License :: OSI Approved :: GNU Lesser General Public License v3 (LGPLv3)
Classifier: Intended Audience :: Developers
Classifier: Operating System :: MacOS :: MacOS X
Classifier: Operating System :: Microsoft :: Windows
Classifier: Development Status :: 5 - Production/Stable
Classifier: Programming Language :: Python :: 3
Requires-Python: >=3.8
License-File: LICENSE.txt
